design.sv
//-----------------keypad module for decimal to bcd conversion----------------
module keypad(i1,i2,i3,i4,i5,i6,i7,i8,i9,i0,open,clear,set,bcd,pressed);
  input i1,i2,i3,i4,i5,i6,i7,i8,i9,i0,open,clear,set;
  output [3:0]bcd;
  output pressed;
  assign bcd[3] = i8 || i9;
  assign bcd[2] = i4 || i5 || i6 || i7;
  assign bcd[1] = i2 || i3 || i6 || i7;
  assign bcd[0] = i1 || i3 || i5 || i7 || i9;
  assign pressed = i1||i2||i3||i4||i5||i6||i0||i9||i8||i7||clear;
endmodule



//-------------top module-----------------------------------------
module dlock(I1,I2,I3,I4,I5,I6,I7,I8,I9,I0,OPEN,CLOSE,SET,LOCK,RESET);
  input I1,I2,I3,I4,I5,I6,I7,I8,I9,I0,OPEN,CLOSE,SET,RESET;
  output reg LOCK;
  wire[3:0] BCD; //bcd from keypad
  reg address; //address=0 to store in first memory,address=1 to store in second memory
  wire setpassword; //if setpassword=1 new password can be set
  wire p; //detect if button is pressed
  reg [3:0] digit1; //first digit
  reg [3:0] digit2; //second digit
  reg [3:0] pwd1; //first digit of password
  reg [3:0] pwd2; //second digit of password
  wire EQ; //EQ=1 if password = entered value
  
 
  
//------instantiating keypad module------------------------
  keypad k1(  
    .i1(I1),.i2(I2),.i3(I3),.i4(I4),.i5(I5),        		 
    .i6(I6),.i7(I7),.i8(I8),.i9(I9),.i0(I0),.open(OPEN),
    .clear(CLOSE),.set(SET),.bcd(BCD),.pressed(p)
     );
  
  

//resets password to 0 if 'RESET' pressed or stores bcd from keypad if 'RESET' not pressed
  always @(posedge p or posedge RESET) 
    begin
      if(RESET)
        begin
          address <= 0;
          pwd1 <= 0;
          pwd2 <= 0;
        end
      else
        begin
          if(!address)
            begin
              digit1 <= BCD;
              address <= 1;
            end
          else
            begin
              digit2 <= BCD;
              address <= 0;
            end
        end
    end
  
  
  
  assign EQ = ({digit1,digit2}=={pwd1,pwd2});//EQ = 1 if entered value equals password
  assign setpassword = LOCK & SET;//if pwd equals and set password pressed
  
  
  
  
  //sets new password 
  always @(posedge setpassword)
    begin
      pwd1 <= digit1;
      pwd2 <= digit2;
    end
  
  
  //open LOCK(LOCK=1) if 'OPEN' PRESSED  OR  RESETS LOCK AND KEYPAD MEMORY TO 0 IF 'CLOSE' PRESSED
  always @(posedge OPEN or posedge CLOSE)
    begin
      if(CLOSE)
        begin
          LOCK <= 0;
          digit1 <= 0;
          digit2 <= 0;
        end
      else
        LOCK <= EQ;
    end
endmodule

testbench.sv
module dlock_tb;
  
  reg T1,T2,T3,T4,T5,T6,T7,T8,T9,T0,O,S,C,R;
  wire L;
  
  dlock d1(
    .I1(T1),.I2(T2),.I3(T3),
    .I4(T4),.I5(T5),.I6(T6),
    .I7(T7),.I8(T8),.I9(T9),
    .I0(T0),.OPEN(O),.CLOSE(C),
    .SET(S),.LOCK(L),.RESET(R)
  );
  
  
  initial begin
    $dumpfile("dump.vcd");
    $dumpvars(2);
//--------------------------------------PRESSING RESET BUTTON----------------------------------------    
    T1 = 1'b0;
    T2 = 1'b0;
    T3 = 1'b0;
    T4 = 1'b0;
    T5 = 1'b0;
    T6 = 1'b0;
    T7 = 1'b0;
    T8 = 1'b0;
    T9 = 1'b0;
    T0 = 1'b0;
    O  = 1'b0;
    S  = 1'b0;
    C  = 1'b0;
    R  = 1'b1;
    #10;
    $display("PRESSING RESET BUTTON\nRESET :%b, OPEN:%b, CLOSE:%b, SET:%b, KEYPAD:%8b, PASSWORD:%8b,EQUAL:%b, LOCK:%b",R,O,C,S,{d1.digit1,d1.digit2},{d1.pwd1,d1.pwd2},d1.EQ,L);
    
// ---------------------------------RELEASING RESET BUTTON-------------------------------------------   
    #10;
    T1 = 1'b0;
    T2 = 1'b0;
    T3 = 1'b0;
    T4 = 1'b0;
    T5 = 1'b0;
    T6 = 1'b0;
    T7 = 1'b0;
    T8 = 1'b0;
    T9 = 1'b0;
    T0 = 1'b0;
    O  = 1'b0;
    S  = 1'b0;
    C  = 1'b0;
    R  = 1'b0;    
    #10;
    $display("RESET :%b, OPEN:%b, CLOSE:%b, SET:%b, KEYPAD:%8b, PASSWORD:%8b,EQUAL:%b, LOCK:%b\n",R,O,C,S,{d1.digit1,d1.digit2},{d1.pwd1,d1.pwd2},d1.EQ,L);  
    
//--------------------------TEST WHEN CORRECT PASSWORD ENTERED-----------------------------------------   
//-----------------------------------------------------------------------------------------------------
    
    $display("TEST WHEN CORRECT PASSWORD ENTERED");
//-------------------------------ENTERING FIRST DIGIT TO CHECK PASSWORD-----------------------------    
    #10;
    T1 = 1'b0;
    T2 = 1'b0;
    T3 = 1'b0;
    T4 = 1'b0;
    T5 = 1'b0;
    T6 = 1'b0;
    T7 = 1'b0;
    T8 = 1'b0;
    T9 = 1'b0;
    T0 = 1'b1;
    O  = 1'b0;
    S  = 1'b0;
    C  = 1'b0;
    R  = 1'b0;    
    #10;
    $display("ENTERING FIRST DIGIT\nRESET :%b, OPEN:%b, CLOSE:%b, SET:%b, KEYPAD:%8b, PASSWORD:%8b,EQUAL:%b, LOCK:%b",R,O,C,S,{d1.digit1,d1.digit2},{d1.pwd1,d1.pwd2},d1.EQ,L);
    
//----------------------------RELEASING BUTTON OF FIRST DIGIT--------------------------------------    
    
    #10;
    T1 = 1'b0;
    T2 = 1'b0;
    T3 = 1'b0;
    T4 = 1'b0;
    T5 = 1'b0;
    T6 = 1'b0;
    T7 = 1'b0;
    T8 = 1'b0;
    T9 = 1'b0;
    T0 = 1'b0;
    O  = 1'b0;
    S  = 1'b0;
    C  = 1'b0;
    R  = 1'b0;    
    #10;
    $display("RESET :%b, OPEN:%b, CLOSE:%b, SET:%b, KEYPAD:%8b, PASSWORD:%8b,EQUAL:%b, LOCK:%b",R,O,C,S,{d1.digit1,d1.digit2},{d1.pwd1,d1.pwd2},d1.EQ,L);
    
//--------------------------------ENTERING SECOND DIGIT-----------------------------------------    
    #10;
    T1 = 1'b0;
    T2 = 1'b0;
    T3 = 1'b0;
    T4 = 1'b0;
    T5 = 1'b0;
    T6 = 1'b0;
    T7 = 1'b0;
    T8 = 1'b0;
    T9 = 1'b0;
    T0 = 1'b1;
    O  = 1'b0;
    S  = 1'b0;
    C  = 1'b0;
    R  = 1'b0;    
    #10;
    $display("ENTERING SECOND DIGIT\nRESET :%b, OPEN:%b, CLOSE:%b, SET:%b, KEYPAD:%8b, PASSWORD:%8b,EQUAL:%b, LOCK:%b",R,O,C,S,{d1.digit1,d1.digit2},{d1.pwd1,d1.pwd2},d1.EQ,L);
      
//------------------------------RELEASING BUTTON OF SECOND DIGIT---------------------------------    
    #10;
    T1 = 1'b0;
    T2 = 1'b0;
    T3 = 1'b0;
    T4 = 1'b0;
    T5 = 1'b0;
    T6 = 1'b0;
    T7 = 1'b0;
    T8 = 1'b0;
    T9 = 1'b0;
    T0 = 1'b0;
    O  = 1'b0;
    S  = 1'b0;
    C  = 1'b0;
    R  = 1'b0;    
    #10;
    $display("RESET :%b, OPEN:%b, CLOSE:%b, SET:%b, KEYPAD:%8b, PASSWORD:%8b,EQUAL:%b, LOCK:%b",R,O,C,S,{d1.digit1,d1.digit2},{d1.pwd1,d1.pwd2},d1.EQ,L);
    
    
//------------------------PRESSING OPEN BUTTON---------------------------------------------    
    #10;
    T1 = 1'b0;
    T2 = 1'b0;
    T3 = 1'b0;
    T4 = 1'b0;
    T5 = 1'b0;
    T6 = 1'b0;
    T7 = 1'b0;
    T8 = 1'b0;
    T9 = 1'b0;
    T0 = 1'b0;
    O  = 1'b1;
    S  = 1'b0;
    C  = 1'b0;
    R  = 1'b0;    
    #10;
    $display("PRESSING OPEN BUTTON TO OPEN LOCK\nRESET :%b, OPEN:%b, CLOSE:%b, SET:%b, KEYPAD:%8b, PASSWORD:%8b,EQUAL:%b, LOCK:%b",R,O,C,S,{d1.digit1,d1.digit2},{d1.pwd1,d1.pwd2},d1.EQ,L);
    
    
//---------------------------------RELEASING OPEN BUTTON----------------------------------    
    #10;
    T1 = 1'b0;
    T2 = 1'b0;
    T3 = 1'b0;
    T4 = 1'b0;
    T5 = 1'b0;
    T6 = 1'b0;
    T7 = 1'b0;
    T8 = 1'b0;
    T9 = 1'b0;
    T0 = 1'b0;
    O  = 1'b0;
    S  = 1'b0;
    C  = 1'b0;
    R  = 1'b0;    
    #10;
    $display("RESET :%b, OPEN:%b, CLOSE:%b, SET:%b, KEYPAD:%8b, PASSWORD:%8b,EQUAL:%b, LOCK:%b",R,O,C,S,{d1.digit1,d1.digit2},{d1.pwd1,d1.pwd2},d1.EQ,L);
    
//-------------------ENTERING FIRST DIGIT OF NEW PASSWORD--------------------------------------------    
    #10;
    T1 = 1'b0;
    T2 = 1'b1;
    T3 = 1'b0;
    T4 = 1'b0;
    T5 = 1'b0;
    T6 = 1'b0;
    T7 = 1'b0;
    T8 = 1'b0;
    T9 = 1'b0;
    T0 = 1'b0;
    O  = 1'b0;
    S  = 1'b0;
    C  = 1'b0;
    R  = 1'b0;    
    #10;
    $display("ENTERING FIRST DIGIT OF NEW PASSWORD\nRESET :%b, OPEN:%b, CLOSE:%b, SET:%b, KEYPAD:%8b, PASSWORD:%8b,EQUAL:%b, LOCK:%b",R,O,C,S,{d1.digit1,d1.digit2},{d1.pwd1,d1.pwd2},d1.EQ,L);
    
    
//---------------------RELEASING BUTTON-------------------------------------------    
        #10;
    T1 = 1'b0;
    T2 = 1'b0;
    T3 = 1'b0;
    T4 = 1'b0;
    T5 = 1'b0;
    T6 = 1'b0;
    T7 = 1'b0;
    T8 = 1'b0;
    T9 = 1'b0;
    T0 = 1'b0;
    O  = 1'b0;
    S  = 1'b0;
    C  = 1'b0;
    R  = 1'b0;    
    #10;
    $display("RESET :%b, OPEN:%b, CLOSE:%b, SET:%b, KEYPAD:%8b, PASSWORD:%8b,EQUAL:%b, LOCK:%b",R,O,C,S,{d1.digit1,d1.digit2},{d1.pwd1,d1.pwd2},d1.EQ,L);
    
//-----------------ENTERING SECOND DIGIT------------------------------    
    #10;
    T1 = 1'b0;
    T2 = 1'b0;
    T3 = 1'b0;
    T4 = 1'b0;
    T5 = 1'b1;
    T6 = 1'b0;
    T7 = 1'b0;
    T8 = 1'b0;
    T9 = 1'b0;
    T0 = 1'b0;
    O  = 1'b0;
    S  = 1'b0;
    C  = 1'b0;
    R  = 1'b0;    
    #10;
    $display("ENETERING SECOND DIGIT OF NEW PASSWORD\nRESET :%b, OPEN:%b, CLOSE:%b, SET:%b, KEYPAD:%8b, PASSWORD:%8b,EQUAL:%b, LOCK:%b",R,O,C,S,{d1.digit1,d1.digit2},{d1.pwd1,d1.pwd2},d1.EQ,L);
    
//------------------------------RELEASING BUTTON---------------------------------------    
    #10;
    T1 = 1'b0;
    T2 = 1'b0;
    T3 = 1'b0;
    T4 = 1'b0;
    T5 = 1'b0;
    T6 = 1'b0;
    T7 = 1'b0;
    T8 = 1'b0;
    T9 = 1'b0;
    T0 = 1'b0;
    O  = 1'b0;
    S  = 1'b0;
    C  = 1'b0;
    R  = 1'b0;    
    #10;
    $display("RESET :%b, OPEN:%b, CLOSE:%b, SET:%b, KEYPAD:%8b, PASSWORD:%8b,EQUAL:%b, LOCK:%b",R,O,C,S,{d1.digit1,d1.digit2},{d1.pwd1,d1.pwd2},d1.EQ,L);
    
    
//---------------------------PRESSING SET PASSWORD BUTTON------------------------------------    
    #10;
    T1 = 1'b0;
    T2 = 1'b0;
    T3 = 1'b0;
    T4 = 1'b0;
    T5 = 1'b0;
    T6 = 1'b0;
    T7 = 1'b0;
    T8 = 1'b0;
    T9 = 1'b0;
    T0 = 1'b0;
    O  = 1'b0;
    S  = 1'b1;
    C  = 1'b0;
    R  = 1'b0;    
    #10;
    $display("PRESSING SET PASSWORD BUTTON\nRESET :%b, OPEN:%b, CLOSE:%b, SET:%b, KEYPAD:%8b, PASSWORD:%8b,EQUAL:%b, LOCK:%b",R,O,C,S,{d1.digit1,d1.digit2},{d1.pwd1,d1.pwd2},d1.EQ,L);
    
    
//----------------------RELEASING BUTTON--------------------------------------------    
    #10;
    T1 = 1'b0;
    T2 = 1'b0;
    T3 = 1'b0;
    T4 = 1'b0;
    T5 = 1'b0;
    T6 = 1'b0;
    T7 = 1'b0;
    T8 = 1'b0;
    T9 = 1'b0;
    T0 = 1'b0;
    O  = 1'b0;
    S  = 1'b0;
    C  = 1'b0;
    R  = 1'b0;    
    #10;
    $display("RESET :%b, OPEN:%b, CLOSE:%b, SET:%b, KEYPAD:%8b, PASSWORD:%8b,EQUAL:%b, LOCK:%b",R,O,C,S,{d1.digit1,d1.digit2},{d1.pwd1,d1.pwd2},d1.EQ,L);
    
    
//----------------------PRESSING CLOSE BUTTON--------------------------------------------------    
    #10;
    T1 = 1'b0;
    T2 = 1'b0;
    T3 = 1'b0;
    T4 = 1'b0;
    T5 = 1'b0;
    T6 = 1'b0;
    T7 = 1'b0;
    T8 = 1'b0;
    T9 = 1'b0;
    T0 = 1'b0;
    O  = 1'b0;
    S  = 1'b0;
    C  = 1'b1;
    R  = 1'b0;    
    #10;
    $display("PRESSING CLOSE BUTTON\nRESET :%b, OPEN:%b, CLOSE:%b, SET:%b, KEYPAD:%8b, PASSWORD:%8b,EQUAL:%b, LOCK:%b",R,O,C,S,{d1.digit1,d1.digit2},{d1.pwd1,d1.pwd2},d1.EQ,L);
    
    
    
//-----------------------RELEASING BUTTON--------------------------------------------------------------    
    #10;
    T1 = 1'b0;
    T2 = 1'b0;
    T3 = 1'b0;
    T4 = 1'b0;
    T5 = 1'b0;
    T6 = 1'b0;
    T7 = 1'b0;
    T8 = 1'b0;
    T9 = 1'b0;
    T0 = 1'b0;
    O  = 1'b0;
    S  = 1'b0;
    C  = 1'b0;
    R  = 1'b0;    
    #10;
    $display("RESET :%b, OPEN:%b, CLOSE:%b, SET:%b, KEYPAD:%8b, PASSWORD:%8b,EQUAL:%b, LOCK:%b",R,O,C,S,{d1.digit1,d1.digit2},{d1.pwd1,d1.pwd2},d1.EQ,L);

    
    
    
//--------------------------TEST WHEN WRONG PASSWORD ENTERED------------------------------------------    
    
    $display("\nTEST WHEN WRONG PASSWORD ENTERED");        
//-------------------------------ENTERING FIRST DIGIT TO CHECK PASSWORD-----------------------------    
    #10;
    T1 = 1'b0;
    T2 = 1'b0;
    T3 = 1'b0;
    T4 = 1'b0;
    T5 = 1'b0;
    T6 = 1'b0;
    T7 = 1'b0;
    T8 = 1'b0;
    T9 = 1'b0;
    T0 = 1'b1;
    O  = 1'b0;
    S  = 1'b0;
    C  = 1'b0;
    R  = 1'b0;    
    #10;
    $display("ENTERING FIRST DIGIT\nRESET :%b, OPEN:%b, CLOSE:%b, SET:%b, KEYPAD:%8b, PASSWORD:%8b,EQUAL:%b, LOCK:%b",R,O,C,S,{d1.digit1,d1.digit2},{d1.pwd1,d1.pwd2},d1.EQ,L);
    
//----------------------------RELEASING BUTTON OF FIRST DIGIT--------------------------------------    
    
    #10;
    T1 = 1'b0;
    T2 = 1'b0;
    T3 = 1'b0;
    T4 = 1'b0;
    T5 = 1'b0;
    T6 = 1'b0;
    T7 = 1'b0;
    T8 = 1'b0;
    T9 = 1'b0;
    T0 = 1'b0;
    O  = 1'b0;
    S  = 1'b0;
    C  = 1'b0;
    R  = 1'b0;    
    #10;
    $display("RESET :%b, OPEN:%b, CLOSE:%b, SET:%b, KEYPAD:%8b, PASSWORD:%8b,EQUAL:%b, LOCK:%b",R,O,C,S,{d1.digit1,d1.digit2},{d1.pwd1,d1.pwd2},d1.EQ,L);
    
//--------------------------------ENTERING SECOND DIGIT-----------------------------------------    
    #10;
    T1 = 1'b0;
    T2 = 1'b0;
    T3 = 1'b0;
    T4 = 1'b0;
    T5 = 1'b0;
    T6 = 1'b0;
    T7 = 1'b0;
    T8 = 1'b0;
    T9 = 1'b0;
    T0 = 1'b1;
    O  = 1'b0;
    S  = 1'b0;
    C  = 1'b0;
    R  = 1'b0;    
    #10;
    $display("ENTERING SECOND DIGIT\nRESET :%b, OPEN:%b, CLOSE:%b, SET:%b, KEYPAD:%8b, PASSWORD:%8b,EQUAL:%b, LOCK:%b",R,O,C,S,{d1.digit1,d1.digit2},{d1.pwd1,d1.pwd2},d1.EQ,L);
      
//------------------------------RELEASING BUTTON OF SECOND DIGIT---------------------------------    
    #10;
    T1 = 1'b0;
    T2 = 1'b0;
    T3 = 1'b0;
    T4 = 1'b0;
    T5 = 1'b0;
    T6 = 1'b0;
    T7 = 1'b0;
    T8 = 1'b0;
    T9 = 1'b0;
    T0 = 1'b0;
    O  = 1'b0;
    S  = 1'b0;
    C  = 1'b0;
    R  = 1'b0;    
    #10;
    $display("RESET :%b, OPEN:%b, CLOSE:%b, SET:%b, KEYPAD:%8b, PASSWORD:%8b,EQUAL:%b, LOCK:%b",R,O,C,S,{d1.digit1,d1.digit2},{d1.pwd1,d1.pwd2},d1.EQ,L);
    
    
//------------------------PRESSING OPEN BUTTON---------------------------------------------    
    #10;
    T1 = 1'b0;
    T2 = 1'b0;
    T3 = 1'b0;
    T4 = 1'b0;
    T5 = 1'b0;
    T6 = 1'b0;
    T7 = 1'b0;
    T8 = 1'b0;
    T9 = 1'b0;
    T0 = 1'b0;
    O  = 1'b1;
    S  = 1'b0;
    C  = 1'b0;
    R  = 1'b0;    
    #10;
    $display("PRESSING OPEN BUTTON TO OPEN LOCK\nRESET :%b, OPEN:%b, CLOSE:%b, SET:%b, KEYPAD:%8b, PASSWORD:%8b,EQUAL:%b, LOCK:%b",R,O,C,S,{d1.digit1,d1.digit2},{d1.pwd1,d1.pwd2},d1.EQ,L);
    
    
//---------------------------------RELEASING OPEN BUTTON----------------------------------    
    #10;
    T1 = 1'b0;
    T2 = 1'b0;
    T3 = 1'b0;
    T4 = 1'b0;
    T5 = 1'b0;
    T6 = 1'b0;
    T7 = 1'b0;
    T8 = 1'b0;
    T9 = 1'b0;
    T0 = 1'b0;
    O  = 1'b0;
    S  = 1'b0;
    C  = 1'b0;
    R  = 1'b0;    
    #10;
    $display("RESET :%b, OPEN:%b, CLOSE:%b, SET:%b, KEYPAD:%8b, PASSWORD:%8b,EQUAL:%b, LOCK:%b",R,O,C,S,{d1.digit1,d1.digit2},{d1.pwd1,d1.pwd2},d1.EQ,L);
    
//-------------------ENTERING FIRST DIGIT OF NEW PASSWORD--------------------------------------------    
    #10;
    T1 = 1'b0;
    T2 = 1'b0;
    T3 = 1'b0;
    T4 = 1'b0;
    T5 = 1'b0;
    T6 = 1'b0;
    T7 = 1'b1;
    T8 = 1'b0;
    T9 = 1'b0;
    T0 = 1'b0;
    O  = 1'b0;
    S  = 1'b0;
    C  = 1'b0;
    R  = 1'b0;    
    #10;
    $display("ENTERING FIRST DIGIT OF NEW PASSWORD\nRESET :%b, OPEN:%b, CLOSE:%b, SET:%b, KEYPAD:%8b, PASSWORD:%8b,EQUAL:%b, LOCK:%b",R,O,C,S,{d1.digit1,d1.digit2},{d1.pwd1,d1.pwd2},d1.EQ,L);
    
    
//---------------------RELEASING BUTTON-------------------------------------------    
        #10;
    T1 = 1'b0;
    T2 = 1'b0;
    T3 = 1'b0;
    T4 = 1'b0;
    T5 = 1'b0;
    T6 = 1'b0;
    T7 = 1'b0;
    T8 = 1'b0;
    T9 = 1'b0;
    T0 = 1'b0;
    O  = 1'b0;
    S  = 1'b0;
    C  = 1'b0;
    R  = 1'b0;    
    #10;
    $display("RESET :%b, OPEN:%b, CLOSE:%b, SET:%b, KEYPAD:%8b, PASSWORD:%8b,EQUAL:%b, LOCK:%b",R,O,C,S,{d1.digit1,d1.digit2},{d1.pwd1,d1.pwd2},d1.EQ,L);
    
//-----------------ENTERING SECOND DIGIT------------------------------    
    #10;
    T1 = 1'b0;
    T2 = 1'b0;
    T3 = 1'b0;
    T4 = 1'b0;
    T5 = 1'b0;
    T6 = 1'b0;
    T7 = 1'b1;
    T8 = 1'b0;
    T9 = 1'b0;
    T0 = 1'b0;
    O  = 1'b0;
    S  = 1'b0;
    C  = 1'b0;
    R  = 1'b0;    
    #10;
    $display("ENETERING SECOND DIGIT OF NEW PASSWORD\nRESET :%b, OPEN:%b, CLOSE:%b, SET:%b, KEYPAD:%8b, PASSWORD:%8b,EQUAL:%b, LOCK:%b",R,O,C,S,{d1.digit1,d1.digit2},{d1.pwd1,d1.pwd2},d1.EQ,L);
    
//------------------------------RELEASING BUTTON---------------------------------------    
    #10;
    T1 = 1'b0;
    T2 = 1'b0;
    T3 = 1'b0;
    T4 = 1'b0;
    T5 = 1'b0;
    T6 = 1'b0;
    T7 = 1'b0;
    T8 = 1'b0;
    T9 = 1'b0;
    T0 = 1'b0;
    O  = 1'b0;
    S  = 1'b0;
    C  = 1'b0;
    R  = 1'b0;    
    #10;
    $display("RESET :%b, OPEN:%b, CLOSE:%b, SET:%b, KEYPAD:%8b, PASSWORD:%8b,EQUAL:%b, LOCK:%b",R,O,C,S,{d1.digit1,d1.digit2},{d1.pwd1,d1.pwd2},d1.EQ,L);
    
    
//---------------------------PRESSING SET PASSWORD BUTTON------------------------------------    
    #10;
    T1 = 1'b0;
    T2 = 1'b0;
    T3 = 1'b0;
    T4 = 1'b0;
    T5 = 1'b0;
    T6 = 1'b0;
    T7 = 1'b0;
    T8 = 1'b0;
    T9 = 1'b0;
    T0 = 1'b0;
    O  = 1'b0;
    S  = 1'b1;
    C  = 1'b0;
    R  = 1'b0;    
    #10;
    $display("PRESSING SET PASSWORD BUTTON\nRESET :%b, OPEN:%b, CLOSE:%b, SET:%b, KEYPAD:%8b, PASSWORD:%8b,EQUAL:%b, LOCK:%b",R,O,C,S,{d1.digit1,d1.digit2},{d1.pwd1,d1.pwd2},d1.EQ,L);
    
    
//----------------------RELEASING BUTTON--------------------------------------------    
    #10;
    T1 = 1'b0;
    T2 = 1'b0;
    T3 = 1'b0;
    T4 = 1'b0;
    T5 = 1'b0;
    T6 = 1'b0;
    T7 = 1'b0;
    T8 = 1'b0;
    T9 = 1'b0;
    T0 = 1'b0;
    O  = 1'b0;
    S  = 1'b0;
    C  = 1'b0;
    R  = 1'b0;    
    #10;
    $display("RESET :%b, OPEN:%b, CLOSE:%b, SET:%b, KEYPAD:%8b, PASSWORD:%8b,EQUAL:%b, LOCK:%b",R,O,C,S,{d1.digit1,d1.digit2},{d1.pwd1,d1.pwd2},d1.EQ,L);
    
    
//----------------------PRESSING CLOSE BUTTON--------------------------------------------------    
    #10;
    T1 = 1'b0;
    T2 = 1'b0;
    T3 = 1'b0;
    T4 = 1'b0;
    T5 = 1'b0;
    T6 = 1'b0;
    T7 = 1'b0;
    T8 = 1'b0;
    T9 = 1'b0;
    T0 = 1'b0;
    O  = 1'b0;
    S  = 1'b0;
    C  = 1'b1;
    R  = 1'b0;    
    #10;
    $display("PRESSING CLOSE BUTTON\nRESET :%b, OPEN:%b, CLOSE:%b, SET:%b, KEYPAD:%8b, PASSWORD:%8b,EQUAL:%b, LOCK:%b",R,O,C,S,{d1.digit1,d1.digit2},{d1.pwd1,d1.pwd2},d1.EQ,L);
    
    
    
//-----------------------RELEASING BUTTON--------------------------------------------------------------    
    #10;
    T1 = 1'b0;
    T2 = 1'b0;
    T3 = 1'b0;
    T4 = 1'b0;
    T5 = 1'b0;
    T6 = 1'b0;
    T7 = 1'b0;
    T8 = 1'b0;
    T9 = 1'b0;
    T0 = 1'b0;
    O  = 1'b0;
    S  = 1'b0;
    C  = 1'b0;
    R  = 1'b0;    
    #10;
    $display("RESET :%b, OPEN:%b, CLOSE:%b, SET:%b, KEYPAD:%8b, PASSWORD:%8b,EQUAL:%b, LOCK:%b",R,O,C,S,{d1.digit1,d1.digit2},{d1.pwd1,d1.pwd2},d1.EQ,L);    
    
    
    
    
    end 
endmodule

dump.vcd
$date
	Wed Dec  2 02:12:07 2020
$end
$version
	Icarus Verilog
$end
$timescale
	1s
$end
$scope module dlock_tb $end
$var wire 1 ! L $end
$var reg 1 " C $end
$var reg 1 # O $end
$var reg 1 $ R $end
$var reg 1 % S $end
$var reg 1 & T0 $end
$var reg 1 ' T1 $end
$var reg 1 ( T2 $end
$var reg 1 ) T3 $end
$var reg 1 * T4 $end
$var reg 1 + T5 $end
$var reg 1 , T6 $end
$var reg 1 - T7 $end
$var reg 1 . T8 $end
$var reg 1 / T9 $end
$scope module d1 $end
$var wire 4 0 BCD [3:0] $end
$var wire 1 1 CLOSE $end
$var wire 1 2 EQ $end
$var wire 1 3 I0 $end
$var wire 1 4 I1 $end
$var wire 1 5 I2 $end
$var wire 1 6 I3 $end
$var wire 1 7 I4 $end
$var wire 1 8 I5 $end
$var wire 1 9 I6 $end
$var wire 1 : I7 $end
$var wire 1 ; I8 $end
$var wire 1 < I9 $end
$var wire 1 = OPEN $end
$var wire 1 > RESET $end
$var wire 1 ? SET $end
$var wire 1 @ p $end
$var wire 1 A setpassword $end
$var reg 1 B LOCK $end
$var reg 1 C address $end
$var reg 4 D digit1 [3:0] $end
$var reg 4 E digit2 [3:0] $end
$var reg 4 F pwd1 [3:0] $end
$var reg 4 G pwd2 [3:0] $end
$upscope $end
$upscope $end
$enddefinitions $end
#0
$dumpvars
b0 G
b0 F
bx E
bx D
0C
xB
0A
0@
0?
1>
0=
0<
0;
0:
09
08
07
06
05
04
03
x2
01
b0 0
0/
0.
0-
0,
0+
0*
0)
0(
0'
0&
0%
1$
0#
0"
x!
$end
#20
0$
0>
#40
1C
b0 D
1@
1&
13
#60
0@
0&
03
#80
0C
b0 E
12
1@
1&
13
#100
0@
0&
03
#120
1B
1!
1#
1=
#140
0#
0=
#160
1C
b10 D
02
1@
b10 0
1(
15
#180
0@
b0 0
0(
05
#200
0C
b101 E
1@
b101 0
1+
18
#220
0@
b0 0
0+
08
#240
b101 G
12
b10 F
1A
1%
1?
#260
0A
0%
0?
#280
1C
b0 E
b0 D
02
0B
0!
1@
1"
11
#300
0@
0"
01
#320
0C
1@
1&
13
#340
0@
0&
03
#360
1C
1@
1&
13
#380
0@
0&
03
#400
1#
1=
#420
0#
0=
#440
0C
b111 E
1@
b111 0
1-
1:
#460
0@
b0 0
0-
0:
#480
1C
b111 D
1@
b111 0
1-
1:
#500
0@
b0 0
0-
0:
#520
1%
1?
#540
0%
0?
#560
0C
b0 E
b0 D
1@
1"
11
#580
0@
0"
01
